{
  "Bongbong": {
    "EyeBattle": "",
    "EyeDead": "Eye_Dead_1_1",
    "EyeDef": "Eye_Default_1_31",
    "EyePanic": "Eye_Panic_1_4",
    "EyebrowBattle": "EyeBrow_Battle_1_7",
    "EyebrowDef": "EyeBrow_1_7",
    "EyebrowPanic": "EyeBrow_Panic_5",
    "FrontHair": "2_3",
    "MouthBattle": "Mouth_Battle_1_7",
    "MouthDef": "Mouth_1_5",
    "MouthPanic": "",
    "RearHair": "4_3",
    "HairColor": "#0000FF",
    "EyeColor": "#FFFFFF"
  },
  "Eke": {
    "EyeBattle": "",
    "EyeDead": "Eye_Dead_1_1",
    "EyeDef": "Eke",
    "EyePanic": "Eye_Panic_1_0",
    "EyebrowBattle": "EyeBrow_Battle_1_1",
    "EyebrowDef": "Eke",
    "EyebrowPanic": "EyeBrow_Panic_2",
    "FrontHair": "Eke",
    "MouthBattle": "Mouth_Battle_1_0",
    "MouthDef": "Eke",
    "MouthPanic": "",
    "RearHair": "RearHair_Transparent",
    "HairColor": "#FFFFFF",
    "EyeColor": "#FFFFFF"
  },
  "Mr.Black": {
    "EyeBattle": "",
    "EyeDead": "Eye_Dead_1_1",
    "EyeDef": "MrBlack",
    "EyePanic": "Eye_Panic_1_0",
    "EyebrowBattle": "EyeBrow_Battle_1_1",
    "EyebrowDef": "MrBlack",
    "EyebrowPanic": "EyeBrow_Panic_3",
    "FrontHair": "MrBlack",
    "MouthBattle": "Mouth_Battle_1_0",
    "MouthDef": "MrBlack",
    "MouthPanic": "",
    "RearHair": "MrBlack",
    "HairColor": "#FFFFFF",
    "EyeColor": "#FFFFFF"
  },
  "Yumeka": {
    "EyeBattle": "",
    "EyeDead": "Eye_Dead_1_2",
    "EyeDef": "Yumeka",
    "EyePanic": "Eye_Panic_1_0",
    "EyebrowBattle": "EyeBrow_Battle_1_5",
    "EyebrowDef": "Yumeka",
    "EyebrowPanic": "EyeBrow_Panic_5",
    "FrontHair": "Yumeka",
    "MouthBattle": "Mouth_Battle_1_0",
    "MouthDef": "Yumeka",
    "MouthPanic": "",
    "RearHair": "Yumeka",
    "HairColor": "#FFFFFF",
    "EyeColor": "#FFFFFF"
  },
  "Kimdaeri": {
    "EyeBattle": "",
    "EyeDead": "Eye_Dead_1_1",
    "EyeDef": "kimdaeri",
    "EyePanic": "Eye_Panic_1_0",
    "EyebrowBattle": "EyeBrow_Battle_1_3",
    "EyebrowDef": "kimdaeri",
    "EyebrowPanic": "EyeBrow_Panic_5",
    "FrontHair": "kimdaeri",
    "MouthBattle": "Mouth_Battle_1_0",
    "MouthDef": "kimdaeri",
    "MouthPanic": "",
    "RearHair": "RearHair_Transparent",
    "HairColor": "#FFFFFF",
    "EyeColor": "#FFFFFF"
  },
  "Aran": {
    "EyeBattle": "",
    "EyeDead": "Eye_Dead_1_2",
    "EyeDef": "Aran",
    "EyePanic": "Eye_Panic_1_0",
    "EyebrowBattle": "EyeBrow_Battle_1_2",
    "EyebrowDef": "Aran",
    "EyebrowPanic": "EyeBrow_Panic_6",
    "FrontHair": "Aran",
    "MouthBattle": "Mouth_Battle_1_0",
    "MouthDef": "Aran",
    "MouthPanic": "",
    "RearHair": "Aran",
    "HairColor": "#FFFFFF",
    "EyeColor": "#FFFFFF"
  },
  "Yetti": {
    "EyeBattle": "",
    "EyeDead": "Eye_Dead_1_2",
    "EyeDef": "Yetti",
    "EyePanic": "Eye_Panic_1_0",
    "EyebrowBattle": "EyeBrow_Battle_1_4",
    "EyebrowDef": "Yetti",
    "EyebrowPanic": "EyeBrow_Panic_3",
    "FrontHair": "Yetti",
    "MouthBattle": "Mouth_Battle_1_0",
    "MouthDef": "Yetti",
    "MouthPanic": "",
    "RearHair": "Yetti",
    "HairColor": "#FFFFFF",
    "EyeColor": "#FFFFFF"
  },
  "Leeheechang": {
    "EyeBattle": "",
    "EyeDead": "Eye_Dead_1_3",
    "EyeDef": "Leeheechang",
    "EyePanic": "Eye_Panic_1_0",
    "EyebrowBattle": "EyeBrow_Battle_1_3",
    "EyebrowDef": "Leeheechang",
    "EyebrowPanic": "EyeBrow_Panic_5",
    "FrontHair": "Leeheechang",
    "MouthBattle": "Mouth_Battle_1_0",
    "MouthDef": "Leeheechang",
    "MouthPanic": "",
    "RearHair": "RearHair_Transparent",
    "HairColor": "#FFFFFF",
    "EyeColor": "#FFFFFF"
  },
  "Alex": {
    "EyeBattle": "",
    "EyeDead": "Eye_Dead_1_1",
    "EyeDef": "Alex",
    "EyePanic": "Eye_Panic_1_0",
    "EyebrowBattle": "EyeBrow_Battle_1_3",
    "EyebrowDef": "Alex",
    "EyebrowPanic": "EyeBrow_Panic_7",
    "FrontHair": "Alex",
    "MouthBattle": "Mouth_Battle_1_0",
    "MouthDef": "Alex",
    "MouthPanic": "",
    "RearHair": "RearHair_Transparent",
    "HairColor": "#FFFFFF",
    "EyeColor": "#FFFFFF"
  },
  "Jeonsangmin": {
    "EyeBattle": "",
    "EyeDead": "Eye_Dead_1_2",
    "EyeDef": "Jeonsangmin",
    "EyePanic": "Eye_Panic_1_0",
    "EyebrowBattle": "EyeBrow_Battle_1_0",
    "EyebrowDef": "Jeonsangmin",
    "EyebrowPanic": "EyeBrow_Panic_4",
    "FrontHair": "Jeonsangmin",
    "MouthBattle": "Mouth_Battle_1_0",
    "MouthDef": "Jeonsangmin",
    "MouthPanic": "",
    "RearHair": "RearHair_Transparent",
    "HairColor": "#FFFFFF",
    "EyeColor": "#FFFFFF"
  },
  "Shepherd": {
    "EyeBattle": "",
    "EyeDead": "Eye_Dead_1_1",
    "EyeDef": "Shepherd",
    "EyePanic": "Eye_Panic_1_0",
    "EyebrowBattle": "EyeBrow_Battle_1_0",
    "EyebrowDef": "Shepherd",
    "EyebrowPanic": "EyeBrow_Panic_5",
    "FrontHair": "Shepherd",
    "MouthBattle": "Mouth_Battle_1_0",
    "MouthDef": "Shepherd",
    "MouthPanic": "",
    "RearHair": "RearHair_Transparent",
    "HairColor": "#FFFFFF",
    "EyeColor": "#FFFFFF"
  },
  "PESCA": {
    "EyeBattle": "",
    "EyeDead": "Eye_Dead_1_2",
    "EyeDef": "PESCA",
    "EyePanic": "Eye_Panic_1_0",
    "EyebrowBattle": "EyeBrow_Battle_1_1",
    "EyebrowDef": "PESCA",
    "EyebrowPanic": "EyeBrow_Panic_4",
    "FrontHair": "PESCA",
    "MouthBattle": "Mouth_Battle_1_0",
    "MouthDef": "PESCA",
    "MouthPanic": "",
    "RearHair": "PESCA",
    "HairColor": "#FFFFFF",
    "EyeColor": "#FFFFFF"
  },
  "Epibinea": {
    "EyeBattle": "",
    "EyeDead": "Eye_Dead_1_2",
    "EyeDef": "Epibinea",
    "EyePanic": "Eye_Panic_1_0",
    "EyebrowBattle": "EyeBrow_Battle_1_1",
    "EyebrowDef": "Epibinea",
    "EyebrowPanic": "EyeBrow_Panic_0",
    "FrontHair": "Epibinea",
    "MouthBattle": "Mouth_Battle_1_0",
    "MouthDef": "Epibinea",
    "MouthPanic": "",
    "RearHair": "Epibinea",
    "HairColor": "#FFFFFF",
    "EyeColor": "#FFFFFF"
  },
  "SpeciaLee": {
    "EyeBattle": "",
    "EyeDead": "Eye_Dead_1_1",
    "EyeDef": "SpecaiLee",
    "EyePanic": "Eye_Panic_1_0",
    "EyebrowBattle": "EyeBrow_Battle_1_1",
    "EyebrowDef": "SpecaiLee",
    "EyebrowPanic": "EyeBrow_Panic_2",
    "FrontHair": "SpecaiLee",
    "MouthBattle": "Mouth_Battle_1_0",
    "MouthDef": "SpecaiLee",
    "MouthPanic": "",
    "RearHair": "RearHair_Transparent",
    "HairColor": "#FFFFFF",
    "EyeColor": "#FFFFFF"
  },
  "Joy Kirbs": {
    "EyeBattle": "",
    "EyeDead": "Eye_Dead_1_1",
    "EyeDef": "JoyKirbs",
    "EyePanic": "Eye_Panic_1_5",
    "EyebrowBattle": "EyeBrow_Battle_1_5",
    "EyebrowDef": "EyeBrow_1_6",
    "EyebrowPanic": "EyeBrow_Panic_2",
    "FrontHair": "JoyKirbsWhite",
    "MouthBattle": "Mouth_Battle_1_2",
    "MouthDef": "Mouth_1_2",
    "MouthPanic": "Mouth_Panic_1_1",
    "RearHair": "4_2",
    "HairColor": "#FFA1CC",
    "EyeColor": "#FFFFFF"
  }
}
